videodev2/__init__.py
videodev2/videodev2.py
videodev2-0.0.2.dist-info/METADATA
videodev2-0.0.2.dist-info/WHEEL
videodev2-0.0.2.dist-info/top_level.txt
videodev2-0.0.2.dist-info/RECORD
