Metadata-Version: 2.4
Name: videodev2
Version: 0.0.2
Summary: Python ctypes bindings for Video4Linux2 (V4L2) API
Home-page: https://github.com/raspberrypi/py-videodev2
Author: Raspberry Pi
License: BSD-3-Clause
Project-URL: Bug Reports, https://github.com/raspberrypi/py-videodev2/issues
Project-URL: Source, https://github.com/raspberrypi/py-videodev2
Keywords: v4l2 video4linux2 linux video capture ctypes
Classifier: Development Status :: 4 - Beta
Classifier: Intended Audience :: Developers
Classifier: Operating System :: POSIX :: Linux
Classifier: Programming Language :: Python :: 3
Classifier: Programming Language :: Python :: 3.6
Classifier: Programming Language :: Python :: 3.7
Classifier: Programming Language :: Python :: 3.8
Classifier: Programming Language :: Python :: 3.9
Classifier: Programming Language :: Python :: 3.10
Classifier: Programming Language :: Python :: 3.11
Classifier: Programming Language :: Python :: 3.12
Classifier: Topic :: Multimedia :: Video :: Capture
Classifier: Topic :: Software Development :: Libraries :: Python Modules
Requires-Python: >=3.6
Provides-Extra: dev
Requires-Dist: twine; extra == "dev"
Requires-Dist: wheel; extra == "dev"
Requires-Dist: build; extra == "dev"
Dynamic: author
Dynamic: classifier
Dynamic: description
Dynamic: description-content-type
Dynamic: home-page
Dynamic: keywords
Dynamic: license
Dynamic: project-url
Dynamic: provides-extra
Dynamic: requires-python
Dynamic: summary
